image_rename/__init__.py
image_rename/cli.py
image_rename/config.py
image_rename/core.py
image_rename/api/__init__.py
image_rename/api/imagehelper.py
image_rename/api/tkmixins.py
image_rename/api/utils.py
image_rename/asset/icon/exif.ico
image_rename/asset/icon/history.ico
image_rename/asset/icon/info.png
image_rename/asset/icon/main.ico
image_rename/asset/icon/paint.png
image_rename/asset/icon/panel.png
image_rename/asset/icon/toolbar.ico
image_rename/template/__init__.py
image_rename/template/base.py
image_rename/template/engine.py
image_rename/template/exceptions.py
image_rename/template/library.py
image_rename/template/node.py
image_rename/template/plugins/__init__.py
image_rename/template/plugins/default_hotkeys.py
image_rename/template/plugins/default_panels.py
image_rename/template/plugins/default_toolbars.py
image_rename/template/plugins/ifdtag.py
image_rename/template/plugins/ifdtag2.py
image_rename/template/plugins/mspaint.py
image_rename/test/__init__.py
image_rename/test/test.py
image_rename/test/image/1.png
image_rename/test/image/2.png
image_rename/test/plugins/__init__.py
image_rename/test/plugins/demo_customize_hotkey.py
image_rename-0.2.0.dist-info/LICENSE
image_rename-0.2.0.dist-info/METADATA
image_rename-0.2.0.dist-info/WHEEL
image_rename-0.2.0.dist-info/entry_points.txt
image_rename-0.2.0.dist-info/top_level.txt
image_rename-0.2.0.dist-info/zip-safe
image_rename-0.2.0.dist-info/RECORD
