Metadata-Version: 2.1
Name: image-rename
Version: 0.2.0
Summary: Rename the picture by looking through the human eye and typing. (you don't need to open the file by yourself)
Home-page: https://github.com/CarsonSlovoka/image-rename/tree/master
Author: Carson
Author-email: jackparadise520a@gmail.com
License: BSD 3-Clause
Project-URL: Homepage, https://github.com/CarsonSlovoka/image-rename/tree/master
Project-URL: Documentation, https://carsonslovoka.github.io/image-rename/en/index.html
Project-URL: Code, https://github.com/CarsonSlovoka/image-rename/tree/master
Project-URL: Issue Tracker, https://github.com/CarsonSlovoka/image-rename/issues
Project-URL: Download, https://github.com/CarsonSlovoka/image-rename/tree/master
Keywords: opencv
Platform: UNKNOWN
Classifier: Development Status :: 3 - Alpha
Classifier: License :: OSI Approved
Classifier: Natural Language :: Chinese (Traditional)
Classifier: Natural Language :: English
Classifier: Operating System :: Microsoft
Classifier: Operating System :: POSIX
Classifier: Operating System :: Unix
Classifier: Operating System :: MacOS
Classifier: Programming Language :: Python :: 3 :: Only
Classifier: Programming Language :: Python :: 3.6
Classifier: Programming Language :: Python :: 3.7
Classifier: Programming Language :: Python :: 3.8
Classifier: Programming Language :: Python :: 3.9
Classifier: Topic :: Desktop Environment :: File Managers
Classifier: Topic :: System :: Filesystems
Requires-Python: >=3.6.2,
Requires-Dist: opencv-python
Requires-Dist: Pillow
Requires-Dist: numpy
Requires-Dist: grid-extractor
